simple_sqlalchemy/__init__.py
simple_sqlalchemy/base.py
simple_sqlalchemy/client.py
simple_sqlalchemy/crud.py
simple_sqlalchemy/py.typed
simple_sqlalchemy/session.py
simple_sqlalchemy/helpers/__init__.py
simple_sqlalchemy/helpers/m2m.py
simple_sqlalchemy/helpers/pagination.py
simple_sqlalchemy/helpers/search.py
simple_sqlalchemy/helpers/string_schema.py
simple_sqlalchemy/postgres/__init__.py
simple_sqlalchemy/postgres/types.py
simple_sqlalchemy/postgres/utils.py
simple_sqlalchemy-0.1.1.dist-info/licenses/LICENSE
simple_sqlalchemy-0.1.1.dist-info/METADATA
simple_sqlalchemy-0.1.1.dist-info/WHEEL
simple_sqlalchemy-0.1.1.dist-info/top_level.txt
simple_sqlalchemy-0.1.1.dist-info/RECORD
