Metadata-Version: 2.4
Name: simple-sqlalchemy
Version: 0.1.1
Summary: A simplified, enhanced SQLAlchemy package with common patterns and utilities
Author-email: Simple SQLAlchemy Contributors <contributors@simple-sqlalchemy.dev>
Maintainer-email: Simple SQLAlchemy Contributors <contributors@simple-sqlalchemy.dev>
License-Expression: MIT
Project-URL: Homepage, https://github.com/simple-sqlalchemy/simple-sqlalchemy
Project-URL: Documentation, https://simple-sqlalchemy.readthedocs.io/
Project-URL: Repository, https://github.com/simple-sqlalchemy/simple-sqlalchemy
Project-URL: Bug Tracker, https://github.com/simple-sqlalchemy/simple-sqlalchemy/issues
Keywords: sqlalchemy,orm,database,crud,pagination,search
Classifier: Development Status :: 4 - Beta
Classifier: Intended Audience :: Developers
Classifier: Operating System :: OS Independent
Classifier: Programming Language :: Python :: 3
Classifier: Programming Language :: Python :: 3.8
Classifier: Programming Language :: Python :: 3.9
Classifier: Programming Language :: Python :: 3.10
Classifier: Programming Language :: Python :: 3.11
Classifier: Programming Language :: Python :: 3.12
Classifier: Topic :: Database
Classifier: Topic :: Software Development :: Libraries :: Python Modules
Classifier: Topic :: Software Development :: Libraries :: Application Frameworks
Requires-Python: >=3.8
License-File: LICENSE
Requires-Dist: sqlalchemy<3.0.0,>=1.4.0
Requires-Dist: typing-extensions>=4.0.0
Provides-Extra: postgres
Requires-Dist: psycopg2-binary>=2.9.0; extra == "postgres"
Requires-Dist: pgvector>=0.1.0; extra == "postgres"
Provides-Extra: docs
Requires-Dist: sphinx>=4.0.0; extra == "docs"
Requires-Dist: sphinx-rtd-theme>=1.0.0; extra == "docs"
Requires-Dist: myst-parser>=0.18.0; extra == "docs"
Requires-Dist: sphinx-autodoc-typehints>=1.12.0; extra == "docs"
Provides-Extra: dev
Requires-Dist: pytest>=7.0.0; extra == "dev"
Requires-Dist: pytest-cov>=4.0.0; extra == "dev"
Requires-Dist: black>=22.0.0; extra == "dev"
Requires-Dist: isort>=5.0.0; extra == "dev"
Requires-Dist: mypy>=1.0.0; extra == "dev"
Requires-Dist: pre-commit>=2.0.0; extra == "dev"
Dynamic: license-file
